vy_organ_sdk/__init__.py
vy_organ_sdk/cancellation.py
vy_organ_sdk/client.py
vy_organ_sdk/codec.py
vy_organ_sdk/factory.py
vy_organ_sdk/handler.py
vy_organ_sdk/launcher.py
vy_organ_sdk/protocol.py
vy_organ_sdk/state.py
vy_organ_sdk/stream.py
vy_organ_sdk/validation.py
vy_organ_sdk/zenoh_client.py
vy_organ_sdk/capabilities/__init__.py
vy_organ_sdk/capabilities/cns_client.py
vy_organ_sdk/capabilities/llm.py
vy_organ_sdk/capabilities/memory.py
vy_organ_sdk/transports/__init__.py
vy_organ_sdk/transports/zenoh_server.py
vy_organ_sdk-2.5.2.dist-info/METADATA
vy_organ_sdk-2.5.2.dist-info/WHEEL
vy_organ_sdk-2.5.2.dist-info/top_level.txt
vy_organ_sdk-2.5.2.dist-info/RECORD
