Metadata-Version: 2.4
Name: vy-organ-sdk
Version: 2.5.2
Summary: SDK for building VY-CNS organs
Author: VY-AGI Team
License-Expression: MIT
Project-URL: Homepage, https://github.com/vinver-labs/vy-organ-sdk
Project-URL: Repository, https://github.com/vinver-labs/vy-organ-sdk
Project-URL: Documentation, https://github.com/vinver-labs/vy-organ-sdk#readme
Keywords: vy,organs,protocol,zenoh,microservices
Classifier: Development Status :: 4 - Beta
Classifier: Intended Audience :: Developers
Classifier: Programming Language :: Python :: 3
Classifier: Programming Language :: Python :: 3.8
Classifier: Programming Language :: Python :: 3.9
Classifier: Programming Language :: Python :: 3.10
Classifier: Programming Language :: Python :: 3.11
Classifier: Programming Language :: Python :: 3.12
Requires-Python: >=3.8
Requires-Dist: eclipse-zenoh>=1.7.2
Requires-Dist: msgpack>=1.0
Dynamic: requires-python
